codimage/__init__.py
codimage/codimage.py
codimage/utils.py
codimage-0.0.2.dist-info/METADATA
codimage-0.0.2.dist-info/RECORD
codimage-0.0.2.dist-info/WHEEL
codimage-0.0.2.dist-info/top_level.txt
