Metadata-Version: 2.1
Name: codimage
Version: 0.0.2
Summary: Encrypt codes and files into picture
Home-page: https://github.com/ianforme/codimage
Author: Sun Weiran
Author-email: sunwrn@gmail.com
License: MIT
Platform: UNKNOWN
Classifier: License :: OSI Approved :: MIT License
Classifier: Programming Language :: Python :: 3
Classifier: Programming Language :: Python :: 3.6
Requires-Dist: numpy
Requires-Dist: pillow
